dataconsistent/__init__.py
dataconsistent-0.0.1.dist-info/AUTHORS.rst
dataconsistent-0.0.1.dist-info/LICENSE.txt
dataconsistent-0.0.1.dist-info/METADATA
dataconsistent-0.0.1.dist-info/WHEEL
dataconsistent-0.0.1.dist-info/top_level.txt
dataconsistent-0.0.1.dist-info/RECORD
