Metadata-Version: 2.1
Name: dataconsistent
Version: 0.0.1
Summary: Computational Advancements in Data-Consistent Inversion
Home-page: https://github.com/mathematicalmichael/thesis.git
Author: Mathematical Michael
Author-email: consistentbayes@gmail.com
License: mit
Project-URL: Documentation, https://pyscaffold.org/
Platform: any
Classifier: Development Status :: 4 - Beta
Classifier: Programming Language :: Python
Requires-Python: >=3.5
Requires-Dist: mud
Provides-Extra: testing
Requires-Dist: pytest ; extra == 'testing'
Requires-Dist: pytest-cov ; extra == 'testing'
